[
    {
        "id": 6,
        "uid": "applications",
        "orgId": 1,
        "name": "applications",
        "type": "influxdb",
        "typeName": "InfluxDB",
        "typeLogoUrl": "public/app/plugins/datasource/influxdb/img/influxdb_logo.svg",
        "access": "proxy",
        "url": "http://influxdb:8086",
        "user": "-",
        "database": "applications",
        "basicAuth": false,
        "isDefault": false,
        "jsonData": {
            "httpMode": "POST",
            "timeInterval": "1s"
        },
        "readOnly": true
    },
    {
        "id": 11,
        "uid": "dhcp",
        "orgId": 1,
        "name": "dhcp",
        "type": "influxdb",
        "typeName": "InfluxDB",
        "typeLogoUrl": "public/app/plugins/datasource/influxdb/img/influxdb_logo.svg",
        "access": "proxy",
        "url": "http://influxdb:8086",
        "user": "-",
        "database": "dhcp",
        "basicAuth": false,
        "isDefault": false,
        "jsonData": {
            "httpMode": "POST",
            "timeInterval": "1s"
        },
        "readOnly": true
    },
    {
        "id": 9,
        "uid": "dns",
        "orgId": 1,
        "name": "dns",
        "type": "influxdb",
        "typeName": "InfluxDB",
        "typeLogoUrl": "public/app/plugins/datasource/influxdb/img/influxdb_logo.svg",
        "access": "proxy",
        "url": "http://influxdb:8086",
        "user": "-",
        "database": "dns",
        "basicAuth": false,
        "isDefault": false,
        "jsonData": {
            "httpMode": "POST",
            "timeInterval": "1s"
        },
        "readOnly": true
    },
    {
        "id": 22,
        "uid": "d170b2fd-28fc-4c20-82e5-dc6f5b7e5b35",
        "orgId": 1,
        "name": "fdc2_applications",
        "type": "influxdb",
        "typeName": "InfluxDB",
        "typeLogoUrl": "public/app/plugins/datasource/influxdb/img/influxdb_logo.svg",
        "access": "proxy",
        "url": "https://10.181.44.196/influxdb",
        "user": "",
        "database": "",
        "basicAuth": true,
        "isDefault": false,
        "jsonData": {
            "dbName": "applications",
            "httpMode": "POST",
            "tlsSkipVerify": true
        },
        "readOnly": false
    },
    {
        "id": 23,
        "uid": "bfe4ad92-29de-4dc8-9f52-50452b448774",
        "orgId": 1,
        "name": "fdc2_dhcp",
        "type": "influxdb",
        "typeName": "InfluxDB",
        "typeLogoUrl": "public/app/plugins/datasource/influxdb/img/influxdb_logo.svg",
        "access": "proxy",
        "url": "https://10.181.44.196/influxdb",
        "user": "",
        "database": "",
        "basicAuth": true,
        "isDefault": false,
        "jsonData": {
            "dbName": "dhcp",
            "httpMode": "POST",
            "tlsSkipVerify": true
        },
        "readOnly": false
    },
    {
        "id": 24,
        "uid": "b8dc55fb-d6ba-4ff4-9bad-10c7c222e82b",
        "orgId": 1,
        "name": "fdc2_dns",
        "type": "influxdb",
        "typeName": "InfluxDB",
        "typeLogoUrl": "public/app/plugins/datasource/influxdb/img/influxdb_logo.svg",
        "access": "proxy",
        "url": "https://10.181.44.196/influxdb",
        "user": "",
        "database": "",
        "basicAuth": true,
        "isDefault": false,
        "jsonData": {
            "dbName": "dns",
            "httpMode": "POST",
            "tlsSkipVerify": true
        },
        "readOnly": false
    },
    {
        "id": 25,
        "uid": "c9428a99-6e32-475f-816e-cfce6c0c4e33",
        "orgId": 1,
        "name": "fdc2_flows",
        "type": "influxdb",
        "typeName": "InfluxDB",
        "typeLogoUrl": "public/app/plugins/datasource/influxdb/img/influxdb_logo.svg",
        "access": "proxy",
        "url": "https://10.181.44.196/influxdb",
        "user": "",
        "database": "",
        "basicAuth": true,
        "isDefault": false,
        "jsonData": {
            "dbName": "flows",
            "httpMode": "POST",
            "tlsSkipVerify": true
        },
        "readOnly": false
    },
    {
        "id": 26,
        "uid": "ed6ad31a-3e93-42c8-991c-9feec50b37b8",
        "orgId": 1,
        "name": "fdc2_https",
        "type": "influxdb",
        "typeName": "InfluxDB",
        "typeLogoUrl": "public/app/plugins/datasource/influxdb/img/influxdb_logo.svg",
        "access": "proxy",
        "url": "https://10.181.44.196/influxdb",
        "user": "",
        "database": "",
        "basicAuth": true,
        "isDefault": false,
        "jsonData": {
            "dbName": "https",
            "httpMode": "POST",
            "tlsSkipVerify": true
        },
        "readOnly": false
    },
    {
        "id": 27,
        "uid": "eb2754bb-f552-4a59-95c5-01c9bebc93e7",
        "orgId": 1,
        "name": "fdc2_icmp",
        "type": "influxdb",
        "typeName": "InfluxDB",
        "typeLogoUrl": "public/app/plugins/datasource/influxdb/img/influxdb_logo.svg",
        "access": "proxy",
        "url": "https://10.181.44.196/influxdb",
        "user": "",
        "database": "",
        "basicAuth": true,
        "isDefault": false,
        "jsonData": {
            "dbName": "icmp",
            "httpMode": "POST",
            "tlsSkipVerify": true
        },
        "readOnly": false
    },
    {
        "id": 28,
        "uid": "a2013412-0f4b-45ee-b78c-e86b541a0638",
        "orgId": 1,
        "name": "fdc2_indicators",
        "type": "influxdb",
        "typeName": "InfluxDB",
        "typeLogoUrl": "public/app/plugins/datasource/influxdb/img/influxdb_logo.svg",
        "access": "proxy",
        "url": "https://10.181.44.196/influxdb",
        "user": "",
        "database": "",
        "basicAuth": true,
        "isDefault": false,
        "jsonData": {
            "dbName": "indicators",
            "httpMode": "POST",
            "tlsSkipVerify": true
        },
        "readOnly": false
    },
    {
        "id": 29,
        "uid": "b34dc897-0358-4055-8995-4a590ea09714",
        "orgId": 1,
        "name": "fdc2_ip_map",
        "type": "influxdb",
        "typeName": "InfluxDB",
        "typeLogoUrl": "public/app/plugins/datasource/influxdb/img/influxdb_logo.svg",
        "access": "proxy",
        "url": "https://10.181.44.196/influxdb",
        "user": "",
        "database": "",
        "basicAuth": true,
        "isDefault": false,
        "jsonData": {
            "dbName": "ip_map",
            "httpMode": "POST",
            "tlsSkipVerify": true
        },
        "readOnly": false
    },
    {
        "id": 30,
        "uid": "f2c9bb9a-43b1-42b8-8932-c832c3bfe02e",
        "orgId": 1,
        "name": "fdc2_tcp",
        "type": "influxdb",
        "typeName": "InfluxDB",
        "typeLogoUrl": "public/app/plugins/datasource/influxdb/img/influxdb_logo.svg",
        "access": "proxy",
        "url": "https://10.181.44.196/influxdb",
        "user": "",
        "database": "",
        "basicAuth": true,
        "isDefault": false,
        "jsonData": {
            "dbName": "tcp",
            "httpMode": "POST",
            "tlsSkipVerify": true
        },
        "readOnly": false
    },
    {
        "id": 5,
        "uid": "flows",
        "orgId": 1,
        "name": "flows",
        "type": "influxdb",
        "typeName": "InfluxDB",
        "typeLogoUrl": "public/app/plugins/datasource/influxdb/img/influxdb_logo.svg",
        "access": "proxy",
        "url": "http://influxdb:8086",
        "user": "-",
        "database": "flows",
        "basicAuth": false,
        "isDefault": false,
        "jsonData": {
            "httpMode": "POST",
            "timeInterval": "1s"
        },
        "readOnly": true
    },
    {
        "id": 20,
        "uid": "b08e3b06-bf15-44e8-adf4-1f61021f3384",
        "orgId": 1,
        "name": "hk3_applications",
        "type": "influxdb",
        "typeName": "InfluxDB",
        "typeLogoUrl": "public/app/plugins/datasource/influxdb/img/influxdb_logo.svg",
        "access": "proxy",
        "url": "https://10.181.45.5/influxdb",
        "user": "",
        "database": "",
        "basicAuth": true,
        "isDefault": false,
        "jsonData": {
            "dbName": "applications",
            "httpMode": "POST",
            "tlsSkipVerify": true
        },
        "readOnly": false
    },
    {
        "id": 16,
        "uid": "eb39ca0b-a427-4963-80e1-d0fb0924f30d",
        "orgId": 1,
        "name": "hk3_dhcp",
        "type": "influxdb",
        "typeName": "InfluxDB",
        "typeLogoUrl": "public/app/plugins/datasource/influxdb/img/influxdb_logo.svg",
        "access": "proxy",
        "url": "https://10.181.45.5/influxdb",
        "user": "",
        "database": "",
        "basicAuth": true,
        "isDefault": false,
        "jsonData": {
            "dbName": "dhcp",
            "httpMode": "POST",
            "tlsSkipVerify": true
        },
        "readOnly": false
    },
    {
        "id": 15,
        "uid": "f2cc7e10-fffc-413b-ad4d-7c46ba3d3f5e",
        "orgId": 1,
        "name": "hk3_dns",
        "type": "influxdb",
        "typeName": "InfluxDB",
        "typeLogoUrl": "public/app/plugins/datasource/influxdb/img/influxdb_logo.svg",
        "access": "proxy",
        "url": "https://10.181.45.5/influxdb",
        "user": "",
        "database": "",
        "basicAuth": true,
        "isDefault": false,
        "jsonData": {
            "dbName": "dns",
            "httpMode": "POST",
            "tlsSkipVerify": true
        },
        "readOnly": false
    },
    {
        "id": 14,
        "uid": "b073ae0a-0cc7-4da0-80fc-0ea2d5b56863",
        "orgId": 1,
        "name": "hk3_flows",
        "type": "influxdb",
        "typeName": "InfluxDB",
        "typeLogoUrl": "public/app/plugins/datasource/influxdb/img/influxdb_logo.svg",
        "access": "proxy",
        "url": "https://10.181.45.5/influxdb",
        "user": "",
        "database": "",
        "basicAuth": true,
        "isDefault": false,
        "jsonData": {
            "dbName": "flows",
            "tlsSkipVerify": true
        },
        "readOnly": false
    },
    {
        "id": 17,
        "uid": "f29d47dd-6af3-4ce7-a344-ba06413f2bba",
        "orgId": 1,
        "name": "hk3_https",
        "type": "influxdb",
        "typeName": "InfluxDB",
        "typeLogoUrl": "public/app/plugins/datasource/influxdb/img/influxdb_logo.svg",
        "access": "proxy",
        "url": "https://10.181.45.5/influxdb",
        "user": "",
        "database": "",
        "basicAuth": true,
        "isDefault": false,
        "jsonData": {
            "dbName": "https",
            "httpMode": "POST",
            "tlsSkipVerify": true
        },
        "readOnly": false
    },
    {
        "id": 18,
        "uid": "c6de4dd7-e6e5-4996-9cb2-887ced3fed2b",
        "orgId": 1,
        "name": "hk3_icmp",
        "type": "influxdb",
        "typeName": "InfluxDB",
        "typeLogoUrl": "public/app/plugins/datasource/influxdb/img/influxdb_logo.svg",
        "access": "proxy",
        "url": "https://10.181.45.5/influxdb",
        "user": "",
        "database": "",
        "basicAuth": true,
        "isDefault": false,
        "jsonData": {
            "dbName": "icmp",
            "httpMode": "POST",
            "tlsSkipVerify": true
        },
        "readOnly": false
    },
    {
        "id": 19,
        "uid": "c518a49f-0dc3-4586-84c6-39c991d43a17",
        "orgId": 1,
        "name": "hk3_indicators",
        "type": "influxdb",
        "typeName": "InfluxDB",
        "typeLogoUrl": "public/app/plugins/datasource/influxdb/img/influxdb_logo.svg",
        "access": "proxy",
        "url": "https://10.181.45.5/influxdb",
        "user": "",
        "database": "",
        "basicAuth": true,
        "isDefault": false,
        "jsonData": {
            "dbName": "indicators",
            "httpMode": "POST",
            "tlsSkipVerify": true
        },
        "readOnly": false
    },
    {
        "id": 21,
        "uid": "ca064a31-43de-40f0-bf29-06a21562bccb",
        "orgId": 1,
        "name": "hk3_ip_map",
        "type": "influxdb",
        "typeName": "InfluxDB",
        "typeLogoUrl": "public/app/plugins/datasource/influxdb/img/influxdb_logo.svg",
        "access": "proxy",
        "url": "https://10.181.45.5/influxdb",
        "user": "",
        "database": "",
        "basicAuth": true,
        "isDefault": false,
        "jsonData": {
            "dbName": "ip_map",
            "httpMode": "POST",
            "tlsSkipVerify": true
        },
        "readOnly": false
    },
    {
        "id": 13,
        "uid": "c78d2a87-2c3b-468a-a5ee-dbb6d860b04f",
        "orgId": 1,
        "name": "hk3_tcp",
        "type": "influxdb",
        "typeName": "InfluxDB",
        "typeLogoUrl": "public/app/plugins/datasource/influxdb/img/influxdb_logo.svg",
        "access": "proxy",
        "url": "https://10.181.45.5/influxdb",
        "user": "",
        "database": "",
        "basicAuth": true,
        "isDefault": false,
        "jsonData": {
            "dbName": "tcp",
            "httpMode": "POST",
            "tlsSkipVerify": true
        },
        "readOnly": false
    },
    {
        "id": 8,
        "uid": "https",
        "orgId": 1,
        "name": "https",
        "type": "influxdb",
        "typeName": "InfluxDB",
        "typeLogoUrl": "public/app/plugins/datasource/influxdb/img/influxdb_logo.svg",
        "access": "proxy",
        "url": "http://influxdb:8086",
        "user": "-",
        "database": "https",
        "basicAuth": false,
        "isDefault": false,
        "jsonData": {
            "httpMode": "POST",
            "timeInterval": "1s"
        },
        "readOnly": true
    },
    {
        "id": 10,
        "uid": "icmp",
        "orgId": 1,
        "name": "icmp",
        "type": "influxdb",
        "typeName": "InfluxDB",
        "typeLogoUrl": "public/app/plugins/datasource/influxdb/img/influxdb_logo.svg",
        "access": "proxy",
        "url": "http://influxdb:8086",
        "user": "-",
        "database": "icmp",
        "basicAuth": false,
        "isDefault": false,
        "jsonData": {
            "httpMode": "POST",
            "timeInterval": "1s"
        },
        "readOnly": true
    },
    {
        "id": 2,
        "uid": "indicators",
        "orgId": 1,
        "name": "indicators",
        "type": "influxdb",
        "typeName": "InfluxDB",
        "typeLogoUrl": "public/app/plugins/datasource/influxdb/img/influxdb_logo.svg",
        "access": "proxy",
        "url": "http://influxdb:8086",
        "user": "-",
        "database": "indicators",
        "basicAuth": false,
        "isDefault": true,
        "jsonData": {
            "httpMode": "POST",
            "timeInterval": "1s"
        },
        "readOnly": true
    },
    {
        "id": 3,
        "uid": "indicators_summary",
        "orgId": 1,
        "name": "Indicators Summary",
        "type": "influxdb",
        "typeName": "InfluxDB",
        "typeLogoUrl": "public/app/plugins/datasource/influxdb/img/influxdb_logo.svg",
        "access": "proxy",
        "url": "http://influxdb:8086",
        "user": "-",
        "database": "indicators_summary",
        "basicAuth": false,
        "isDefault": false,
        "jsonData": {
            "httpMode": "POST"
        },
        "readOnly": true
    },
    {
        "id": 1,
        "uid": "influxdb_health",
        "orgId": 1,
        "name": "InfluxDB Health",
        "type": "influxdb",
        "typeName": "InfluxDB",
        "typeLogoUrl": "public/app/plugins/datasource/influxdb/img/influxdb_logo.svg",
        "access": "proxy",
        "url": "http://influxdb:8086",
        "user": "-",
        "database": "_internal",
        "basicAuth": false,
        "isDefault": false,
        "jsonData": {},
        "readOnly": true
    },
    {
        "id": 7,
        "uid": "ip_map",
        "orgId": 1,
        "name": "ip_map",
        "type": "influxdb",
        "typeName": "InfluxDB",
        "typeLogoUrl": "public/app/plugins/datasource/influxdb/img/influxdb_logo.svg",
        "access": "proxy",
        "url": "http://influxdb:8086",
        "user": "-",
        "database": "ip_map",
        "basicAuth": false,
        "isDefault": false,
        "jsonData": {
            "httpMode": "POST",
            "timeInterval": "1s"
        },
        "readOnly": true
    },
    {
        "id": 12,
        "uid": "ea2a8618-39ad-4e24-95b5-7fc54566189f",
        "orgId": 1,
        "name": "sys",
        "type": "influxdb",
        "typeName": "InfluxDB",
        "typeLogoUrl": "public/app/plugins/datasource/influxdb/img/influxdb_logo.svg",
        "access": "proxy",
        "url": "http://influxdb:8086",
        "user": "",
        "database": "",
        "basicAuth": false,
        "isDefault": false,
        "jsonData": {
            "dbName": "sys",
            "httpMode": "POST"
        },
        "readOnly": false
    },
    {
        "id": 4,
        "uid": "tcp",
        "orgId": 1,
        "name": "tcp",
        "type": "influxdb",
        "typeName": "InfluxDB",
        "typeLogoUrl": "public/app/plugins/datasource/influxdb/img/influxdb_logo.svg",
        "access": "proxy",
        "url": "http://influxdb:8086",
        "user": "-",
        "database": "tcp",
        "basicAuth": false,
        "isDefault": false,
        "jsonData": {
            "httpMode": "POST",
            "timeInterval": "1s"
        },
        "readOnly": true
    }
]